hand_gesture_volume_control/__init__.py
hand_gesture_volume_control-0.1.0.dist-info/licenses/LICENSE
hand_gesture_volume_control-0.1.0.dist-info/METADATA
hand_gesture_volume_control-0.1.0.dist-info/WHEEL
hand_gesture_volume_control-0.1.0.dist-info/top_level.txt
hand_gesture_volume_control-0.1.0.dist-info/RECORD
