Metadata-Version: 2.4
Name: hand-gesture-volume-control
Version: 0.1.0
Summary: التحكم في حجم الصوت من خلال حركة اليد باستخدام MediaPipe و pycaw
Author: Rania Elkholy
Classifier: Programming Language :: Python :: 3
Classifier: License :: OSI Approved :: MIT License
Classifier: Operating System :: Microsoft :: Windows
Requires-Python: >=3.7
License-File: LICENSE
Requires-Dist: opencv-python
Requires-Dist: mediapipe
Requires-Dist: pycaw
Requires-Dist: comtypes
Dynamic: author
Dynamic: classifier
Dynamic: description
Dynamic: description-content-type
Dynamic: license-file
Dynamic: requires-dist
Dynamic: requires-python
Dynamic: summary
